manipulate/__init__.py
manipulate-0.0.0.dev1.dist-info/LICENSE.rst
manipulate-0.0.0.dev1.dist-info/METADATA
manipulate-0.0.0.dev1.dist-info/WHEEL
manipulate-0.0.0.dev1.dist-info/top_level.txt
manipulate-0.0.0.dev1.dist-info/RECORD
